bulkget/__init__.py
bulkget/downloader.py
bulkget/main.py
bulkget/managers.py
bulkget/utils.py
bulkget-0.1.2.dist-info/METADATA
bulkget-0.1.2.dist-info/WHEEL
bulkget-0.1.2.dist-info/entry_points.txt
bulkget-0.1.2.dist-info/RECORD
