Metadata-Version: 2.3
Name: bulkget
Version: 0.1.2
Summary: 
Author: Ayoub G.
Author-email: dev@ayghri.com
Requires-Python: >=3.9,<3.14
Classifier: Programming Language :: Python :: 3
Classifier: Programming Language :: Python :: 3.9
Classifier: Programming Language :: Python :: 3.10
Classifier: Programming Language :: Python :: 3.11
Classifier: Programming Language :: Python :: 3.12
Classifier: Programming Language :: Python :: 3.13
Requires-Dist: aria2p[tui] (>=0.12.1,<0.13.0)
